{"Name":"bbb","Email":"bbb@gmail.com","Password":"{\"iv\":\"5Fnuxhr6vRxBwraNrS5rBQ\",\"v\":1,\"iter\":1000,\"ks\":128,\"ts\":64,\"mode\":\"ccm\",\"adata\":\"\",\"cipher\":\"aes\",\"salt\":\"CRXf0t79bS4\",\"ct\":\"2Um2GXTKawGoGH4\"}","ConfirmPassword":"{\"iv\":\"KFEv8uKFAw9NZmTmZ6QcNA\",\"v\":1,\"iter\":1000,\"ks\":128,\"ts\":64,\"mode\":\"ccm\",\"adata\":\"\",\"cipher\":\"aes\",\"salt\":\"CRXf0t79bS4\",\"ct\":\"4R5E3SMPv2qJreM\"}","FourDigitCode":"0000","AddressOne":{"contactName":"Bhanuka Vimukthi Bandara","mobileNo":"0775320463","streetAddress":"58/A Lewella Road, Kandy","postalCode":"20000","defaultAddress":true},"AddressTwo":null,"UserGender":null,"BirthDay":null,"LoyaltyPoints":1.18,"FirstName":null,"LastName":null}